usefulpy/__init__.py
usefulpy/__main__.py
usefulpy/decorators.py
usefulpy/formatting.py
usefulpy/py.typed
usefulpy/validation.py
usefulpython-0.2.1.dist-info/LICENSE
usefulpython-0.2.1.dist-info/METADATA
usefulpython-0.2.1.dist-info/WHEEL
usefulpython-0.2.1.dist-info/top_level.txt
usefulpython-0.2.1.dist-info/RECORD
