Metadata-Version: 2.1
Name: usefulpython
Version: 0.2.1
Summary: tools for a cleaner πthon experience
Home-page: UNKNOWN
Author: Augustin Garcia
License: GNU AFFERO GENERAL PUBLIC LICENSE
Platform: unix
Platform: linux
Platform: osx
Platform: cygwin
Platform: win32
Classifier: Programming Language :: Python :: 3
Classifier: Operating System :: OS Independent
Requires-Python: >=3.6
License-File: LICENSE
Provides-Extra: testing
Requires-Dist: flake8 (==3.9.2) ; extra == 'testing'
Requires-Dist: pytest (==6.2.5) ; extra == 'testing'
Requires-Dist: pytest-cov (==2.12.1) ; extra == 'testing'
Requires-Dist: mypy (==0.910) ; extra == 'testing'
